pyhtmd
