Metadata-Version: 2.1
Name: pyhtmd
Version: 0.1.2
Summary: A Python HTML to Markdown parser
Home-page: https://github.com/veaba/pyhtmd
Author: veaba
Author-email: godpu@outlook.com
License: UNKNOWN
Keywords: html,markdown,parser,pyhtmd
Platform: any
